{
  "posts": [
    {
      "id": 1,
      "title": "json-server",
      "author": "typicode"
    }
  ],
  "comments": [
    {
      "id": 1,
      "body": "some comment",
      "postId": 1
    }
  ],
  "profile": {
    "name": "typicode"
  },
  "pizzas":[
    {
      "id":0,
      "nome":"Calabresa",
      "precoP":55.55,
      "precoM":65.55,
      "precoG":75.55,
      "image": "../../assets/imagemPizzas/pizzaCalabresa.jpg"
    },
    {
      "id":1,
      "nome":"Frango",
      "precoP":55.55,
      "precoM":65.55,
      "precoG":75.55,
      "image": "../../assets/imagemPizzas/frango.jpg"
    },
    {
      "id":2,
      "nome":"Presunto",
      "precoP":30.33,
      "precoM":65.55,
      "precoG":75.55,
      "image": "../../assets/imagemPizzas/presunto.jpg"
    },
    {
      "id":0,
      "nome":"Calabresa",
      "precoP":55.55,
      "precoM":65.55,
      "precoG":75.55,
      "image": "../../assets/imagemPizzas/pizzaCalabresa.jpg"
    },
    {
      "id":1,
      "nome":"Frango",
      "precoP":55.55,
      "precoM":65.55,
      "precoG":75.55,
      "image": "../../assets/imagemPizzas/frango.jpg"
    },
    {
      "id":2,
      "nome":"Presunto",
      "precoP":30.33,
      "precoM":65.55,
      "precoG":75.55,
      "image": "../../assets/imagemPizzas/presunto.jpg"
    },
    {
      "id":0,
      "nome":"Calabresa",
      "precoP":55.55,
      "precoM":65.55,
      "precoG":75.55,
      "image": "../../assets/imagemPizzas/pizzaCalabresa.jpg"
    },
    {
      "id":1,
      "nome":"Frango",
      "precoP":55.55,
      "precoM":65.55,
      "precoG":75.55,
      "image": "../../assets/imagemPizzas/frango.jpg"
    },
    {
      "id":2,
      "nome":"Presunto",
      "precoP":30.33,
      "precoM":65.55,
      "precoG":75.55,
      "image": "../../assets/imagemPizzas/presunto.jpg"
    }
  ]
}
